csvwlib/__init__.py
csvwlib/converter/CSVWConverter.py
csvwlib/converter/ModelConverter.py
csvwlib/converter/ToJSONConverter.py
csvwlib/converter/ToRDFConverter.py
csvwlib/converter/__init__.py
csvwlib/utils/ATDMUtils.py
csvwlib/utils/CSVUtils.py
csvwlib/utils/DOPUtils.py
csvwlib/utils/DialectUtils.py
csvwlib/utils/MetadataLocator.py
csvwlib/utils/NumericUtils.py
csvwlib/utils/TypeConverter.py
csvwlib/utils/__init__.py
csvwlib/utils/datatypeutils.py
csvwlib/utils/metadata.py
csvwlib/utils/json/CommonProperties.py
csvwlib/utils/json/JSONLDUtils.py
csvwlib/utils/json/__init__.py
csvwlib/utils/rdf/CSVW.py
csvwlib/utils/rdf/Namespaces.py
csvwlib/utils/rdf/OntologyUtils.py
csvwlib/utils/rdf/RDFGraphUtils.py
csvwlib/utils/rdf/RDFUtils.py
csvwlib/utils/rdf/__init__.py
csvwlib/utils/url/AboutUrlutils.py
csvwlib/utils/url/PropertyUrlUtils.py
csvwlib/utils/url/UriTemplateUtils.py
csvwlib/utils/url/ValueUrlUtils.py
csvwlib/utils/url/WellKnownUriResolver.py
csvwlib/utils/url/__init__.py
csvwlib-0.3.2.dist-info/LICENSE
csvwlib-0.3.2.dist-info/METADATA
csvwlib-0.3.2.dist-info/WHEEL
csvwlib-0.3.2.dist-info/top_level.txt
csvwlib-0.3.2.dist-info/RECORD
