Metadata-Version: 2.1
Name: csvwlib
Version: 0.3.2
Summary: Python implementation of CSV on the Web
Home-page: https://github.com/DerwenAI/csvwlib
Author: Aleksander Drozd
Author-email: aleksander.drozd@outlook.com
License: MIT
Project-URL: Bug Tracker, https://github.com/DerwenAI/csvwlib/issues
Project-URL: Source Code, https://github.com/DerwenAI/csvwlib
Keywords: knowledge graph,rdf,controlled vocabulary,csv,tabular data
Platform: UNKNOWN
Classifier: Programming Language :: Python :: 3
Classifier: License :: OSI Approved :: MIT License
Classifier: Operating System :: OS Independent
Classifier: Development Status :: 4 - Beta
Classifier: Intended Audience :: Developers
Classifier: Intended Audience :: Education
Classifier: Intended Audience :: Information Technology
Classifier: Intended Audience :: Science/Research
Classifier: Topic :: Scientific/Engineering :: Artificial Intelligence
Classifier: Topic :: Scientific/Engineering :: Human Machine Interfaces
Classifier: Topic :: Scientific/Engineering :: Information Analysis
Classifier: Topic :: Text Processing :: Indexing
Requires-Python: >=3.6
Requires-Dist: python-dateutil (>=2.6.1)
Requires-Dist: rdflib (>=4.2.2)
Requires-Dist: rdflib-jsonld (>=0.4.0)
Requires-Dist: requests (>=2.20.0)
Requires-Dist: uritemplate (>=3.0.0)
Requires-Dist: language-tags (>=0.4.3)
